{"content_ddd_index.md":"5904f379","content_docker_index.md":"1ce88330","content_io_index.md":"d7eb9051","content_juc_index.md":"b233d54b","content_jvm_index.md":"92ba305a","content_mybatis_index.md":"1692748c","content_netty_index.md":"26c2281f","content_spring boot_index.md":"1d965e12","content_spring cloud_index.md":"60b15172","content_spring_index.md":"b9bb6f15","content_index.md":"bfd0a436","guide_introduce_deploy.md":"0debabab","guide_introduce_intro.md":"514f3d3b","guide_introduce_position.md":"ec604e9c","guide_write_asset-handling.md":"1639a105","guide_write_markdown.md":"a37f37a7","index.md":"9f44fe5a","java_io_index.md":"441105ae","java_juc_index.md":"7e2e0470","java_jvm_index.md":"b859d87d","spring_spring boot_index.md":"9920e714","spring_spring cloud_index.md":"10409e05","spring_spring_index.md":"c0ef9670"}
